{
  "skills": [
    {"skill": "SQL", "rank": 92},
    {"skill": "Python", "rank": 74},
    {"skill": "JavaScript", "rank": 13},
    {"skill": "Machine Learning", "rank": 64},
    {"skill": "Artificial Intelligence", "rank": 47},
    {"skill": "Data Analysis", "rank": 88},
    {"skill": "Database Design", "rank": 56},
    {"skill": "Data Visualization", "rank": 41},
    {"skill": "Web Development", "rank": 51},
    {"skill": "Problem Solving", "rank": 87},
    {"skill": "Communication", "rank": 93}
  ]
}